{
    "data": [
      {
        "id": 1,
        "img": "http://localhost:8000/media/main/project_images/adwaitid.jpg",
        "author": "admin",
        "title": "Remote Education",
        "datePublished": "2022-01-26 18:19:18+00:00",
        "content": "Lorem ipsum dolor sit amet consectetur adipisicing elit. Reprehenderit saepe velit aspernatur dolorem voluptates id ",
        "tags": [
          {
            "tag": "daa",
            "count": 0
          },
          {
            "tag": "DevOps",
            "count": 0
          }
        ],
        "tech_stack": [
          {
            "tech": "Django"
          },
          {
            "tech": "React"
          }
        ],
        "comments": [
          {
            "user": "admin",
            "text": "This project is OP",
            "datePublished": "2022-01-26 18:20:47+00:00"
          }
        ]
      },
      {
        "id": 1,
        "img": "http://localhost:8000/media/main/project_images/adwaitid.jpg",
        "author": "admin",
        "title": "Remote Education",
        "datePublished": "2022-01-26 18:19:18+00:00",
        "content": "Hey hey see my project",
        "tags": [
          {
            "tag": "ML",
            "count": 0
          },
          {
            "tag": "DevOps",
            "count": 0
          }
        ],
        "tech_stack": [
          {
            "tech": "Django"
          },
          {
            "tech": "React"
          }
        ],
        "comments": [
          {
            "user": "admin",
            "text": "This project is OP",
            "datePublished": "2022-01-26 18:20:47+00:00"
          }
        ]
      }
    ]
  }